{"P5": {"labels": ["\u7f8e\u5973"], "postTitle": "\u7f8e\u5973", "postUrl": "post/mei-nv.html", "createdDate": "2025-01-27", "dateLabelColor": "#0969da"}, "P4": {"labels": ["\u82f9\u679c"], "postTitle": "\u7684\u6cd5\u56fd\u6d77\u519b", "postUrl": "post/de-fa-guo-hai-jun.html", "createdDate": "2025-01-27", "dateLabelColor": "#0969da"}, "P3": {"labels": ["Label"], "postTitle": "\u4e1c\u98ce\u80a1\u4efd\u5408\u8ba1", "postUrl": "post/dong-feng-gu-fen-he-ji.html", "createdDate": "2025-01-27", "dateLabelColor": "#0969da"}, "P2": {"labels": ["Label"], "postTitle": "\u7b2c\u4e8c\u7bc7\u535a\u5ba2", "postUrl": "post/di-er-pian-bo-ke.html", "createdDate": "2025-01-27", "dateLabelColor": "#0969da"}, "P1": {"labels": ["\u5b89\u5353"], "postTitle": "\u7b2c\u4e00\u54c1\u535a\u5ba2", "postUrl": "post/di-yi-pin-bo-ke.html", "createdDate": "2025-01-27", "dateLabelColor": "#0969da"}, "labelColorDict": {"bug": "#d73a4a", "documentation": "#0075ca", "duplicate": "#cfd3d7", "enhancement": "#a2eeef", "good first issue": "#7057ff", "help wanted": "#008672", "invalid": "#e4e669", "Label": "#aaaaaa", "question": "#d876e3", "wontfix": "#ffffff", "\u5b89\u5353": "#aaaaaa", "\u7f8e\u5973": "#aaaaaa", "\u82f9\u679c": "#aaaaaa"}}